wavesurfer/__init__.py
wavesurfer/alignment.py
wavesurfer/player.py
wavesurfer/timer.py
wavesurfer/utils.py
wavesurfer/configs/player.json
wavesurfer/js/bootstrap.bundle.min.js
wavesurfer/js/pcm-player.js
wavesurfer/js/wavesurfer.js
wavesurfer/js/wavesurfer.min.js
wavesurfer/js/plugins/hover.min.js
wavesurfer/js/plugins/minimap.min.js
wavesurfer/js/plugins/regions.min.js
wavesurfer/js/plugins/spectrogram-windowed.min.js
wavesurfer/js/plugins/spectrogram.min.js
wavesurfer/js/plugins/timeline.min.js
wavesurfer/js/plugins/zoom.min.js
wavesurfer/templates/wavesurfer.txt
wavesurfer-0.3.8.dist-info/licenses/LICENSE
wavesurfer-0.3.8.dist-info/METADATA
wavesurfer-0.3.8.dist-info/WHEEL
wavesurfer-0.3.8.dist-info/top_level.txt
wavesurfer-0.3.8.dist-info/RECORD
