Metadata-Version: 2.4
Name: wavesurfer
Version: 0.3.8
Summary: TorchAudio Forced Aligner
Author-email: Zhendong Peng <pzd17@tsinghua.org.cn>
License: BSD 2-Clause License
Project-URL: Homepage, https://github.com/pengzhendong/wavesurfer
Project-URL: Documentation, https://github.com/pengzhendong/wavesurfer#readme
Project-URL: BugTracker, https://github.com/pengzhendong/wavesurfer/issues
Classifier: Programming Language :: Python :: 3
Classifier: Operating System :: OS Independent
Requires-Python: >=3.8
License-File: LICENSE
Requires-Dist: audiolab
Requires-Dist: jinja2
Requires-Dist: matplotlib
Requires-Dist: tgt
Dynamic: license-file
